{
  "author": {
    "displayName": "[unknown]",
    "steamID": 76561197992933636
  },
  "displayName": "Escape from Empire",
  "id": 465459892,
  "description": "An awesome community level",
  "fileName": "city",
  "upvotes": 28,
  "downvotes": 31,
  "leaderboard": [
    {
      "player": {
        "displayName": "IllKIllU",
        "steamID": 76561198216635512
      },
      "time": 31710
    },
    {
      "player": {
        "displayName": "wit",
        "steamID": 76561198047147439
      },
      "time": 92050
    },
    {
      "player": {
        "displayName": "guest35",
        "steamID": 76561198089106562
      },
      "time": 97340
    },
    {
      "player": {
        "displayName": "fruitspunchsamuraiG",
        "steamID": 76561198079757505
      },
      "time": 100100
    },
    {
      "player": {
        "displayName": "JackAwsome2000",
        "steamID": 76561198090983403
      },
      "time": 107290
    },
    {
      "player": {
        "displayName": "ferreus",
        "steamID": 76561198040630941
      },
      "time": 111040
    },
    {
      "player": {
        "displayName": "PurpleSuede",
        "steamID": 76561198308735695
      },
      "time": 124670
    },
    {
      "player": {
        "displayName": "Cocoa",
        "steamID": 76561198090548196
      },
      "time": 124710
    },
    {
      "player": {
        "displayName": "Armored Trashbin",
        "steamID": 76561197991243263
      },
      "time": 139900
    },
    {
      "player": {
        "displayName": "d4edalus01",
        "steamID": 76561198126523423
      },
      "time": 154080
    },
    {
      "player": {
        "displayName": "Daniel360n",
        "steamID": 76561198046981902
      },
      "time": 168290
    },
    {
      "player": {
        "displayName": "Firewarrior005",
        "steamID": 76561198068859199
      },
      "time": 170630
    },
    {
      "player": {
        "displayName": "Keiyo",
        "steamID": 76561197990057420
      },
      "time": 173640
    },
    {
      "player": {
        "displayName": "Triazo",
        "steamID": 76561198000691754
      },
      "time": 174020
    },
    {
      "player": {
        "displayName": "Earthnuker",
        "steamID": 76561197993507212
      },
      "time": 186640
    },
    {
      "player": {
        "displayName": "Batto",
        "steamID": 76561197962868558
      },
      "time": 186800
    },
    {
      "player": {
        "displayName": "大和魂",
        "steamID": 76561197997603197
      },
      "time": 191130
    },
    {
      "player": {
        "displayName": "Dark_ION57_вук",
        "steamID": 76561198025480120
      },
      "time": 221040
    },
    {
      "player": {
        "displayName": "joltz",
        "steamID": 76561197992301832
      },
      "time": 232930
    },
    {
      "player": {
        "displayName": "-Ω-",
        "steamID": 76561198065040574
      },
      "time": 249590
    },
    {
      "player": {
        "displayName": "DefenderOfHyrule",
        "steamID": 76561198144159516
      },
      "time": 293570
    }
  ]
}