{
  "author": {
    "displayName": "[unknown]",
    "steamID": 76561198142485496
  },
  "displayName": "Blizzard Realm",
  "id": 1095057720,
  "description": "An awesome community level",
  "fileName": "blizzard realm",
  "upvotes": 127,
  "downvotes": 61,
  "leaderboard": [
    {
      "player": {
        "displayName": "PPPaul",
        "steamID": 76561198023567939
      },
      "time": 291010
    },
    {
      "player": {
        "displayName": "Nerf",
        "steamID": 76561198137753179
      },
      "time": 327180
    },
    {
      "player": {
        "displayName": "MCrekna",
        "steamID": 76561198117876048
      },
      "time": 327530
    },
    {
      "player": {
        "displayName": "Thunderskull",
        "steamID": 76561197989191729
      },
      "time": 344190
    },
    {
      "player": {
        "displayName": "Sassy",
        "steamID": 76561198034834458
      },
      "time": 346140
    },
    {
      "player": {
        "displayName": "Skafloodle",
        "steamID": 76561198050560606
      },
      "time": 346240
    },
    {
      "player": {
        "displayName": "WW3 Cat",
        "steamID": 76561198262864175
      },
      "time": 347560
    },
    {
      "player": {
        "displayName": "Blakcbird",
        "steamID": 76561198078169062
      },
      "time": 348450
    },
    {
      "player": {
        "displayName": "Daiyard",
        "steamID": 76561198241184526
      },
      "time": 349420
    },
    {
      "player": {
        "displayName": "Krazy8s",
        "steamID": 76561198078867563
      },
      "time": 349530
    },
    {
      "player": {
        "displayName": "Arriow",
        "steamID": 76561197991899313
      },
      "time": 349690
    },
    {
      "player": {
        "displayName": "Kamikaze901",
        "steamID": 76561198000725310
      },
      "time": 349950
    },
    {
      "player": {
        "displayName": "BRGHOST2.0",
        "steamID": 76561198071923134
      },
      "time": 351550
    },
    {
      "player": {
        "displayName": "OctaGear",
        "steamID": 76561198110656995
      },
      "time": 351770
    },
    {
      "player": {
        "displayName": "Gogethitbyacar",
        "steamID": 76561198071652847
      },
      "time": 352630
    },
    {
      "player": {
        "displayName": "egfdagger2000",
        "steamID": 76561198396873595
      },
      "time": 353210
    },
    {
      "player": {
        "displayName": "PhantomRama",
        "steamID": 76561198142485496
      },
      "time": 353720
    },
    {
      "player": {
        "displayName": "shen",
        "steamID": 76561198127206065
      },
      "time": 354830
    },
    {
      "player": {
        "displayName": "Teco Cruzada",
        "steamID": 76561198235796458
      },
      "time": 355790
    },
    {
      "player": {
        "displayName": "Victory",
        "steamID": 76561198086420605
      },
      "time": 356060
    },
    {
      "player": {
        "displayName": "Chrimbous",
        "steamID": 76561198016951697
      },
      "time": 357720
    },
    {
      "player": {
        "displayName": "smphoto7",
        "steamID": 76561198376081419
      },
      "time": 359920
    },
    {
      "player": {
        "displayName": "Raze Silverwing",
        "steamID": 76561198390749737
      },
      "time": 360830
    },
    {
      "player": {
        "displayName": "🌪Dashie010203🌪",
        "steamID": 76561198093826520
      },
      "time": 360910
    },
    {
      "player": {
        "displayName": "SG-58",
        "steamID": 76561198041276435
      },
      "time": 361560
    },
    {
      "player": {
        "displayName": "Yuki 花",
        "steamID": 76561198081670014
      },
      "time": 361630
    },
    {
      "player": {
        "displayName": "Traplover",
        "steamID": 76561198001043815
      },
      "time": 363810
    },
    {
      "player": {
        "displayName": "giratosxd",
        "steamID": 76561198089235708
      },
      "time": 364050
    },
    {
      "player": {
        "displayName": "lefor0416",
        "steamID": 76561198025350851
      },
      "time": 364420
    },
    {
      "player": {
        "displayName": "Jeff",
        "steamID": 76561198088682770
      },
      "time": 364490
    },
    {
      "player": {
        "displayName": "xka1resx",
        "steamID": 76561198162034923
      },
      "time": 364770
    },
    {
      "player": {
        "displayName": "Medicine The Bun",
        "steamID": 76561198045353768
      },
      "time": 365970
    },
    {
      "player": {
        "displayName": "lamb0",
        "steamID": 76561198015979514
      },
      "time": 367150
    },
    {
      "player": {
        "displayName": "CalKyanite",
        "steamID": 76561198174641774
      },
      "time": 367390
    },
    {
      "player": {
        "displayName": "Subz",
        "steamID": 76561198272361142
      },
      "time": 369920
    },
    {
      "player": {
        "displayName": "Sparkster",
        "steamID": 76561198029443369
      },
      "time": 370880
    },
    {
      "player": {
        "displayName": "Vlyox",
        "steamID": 76561198148812786
      },
      "time": 370960
    },
    {
      "player": {
        "displayName": "Steviation",
        "steamID": 76561198103644187
      },
      "time": 371350
    },
    {
      "player": {
        "displayName": "Eric Andre",
        "steamID": 76561198040722466
      },
      "time": 371440
    },
    {
      "player": {
        "displayName": "Infinite Gaming",
        "steamID": 76561198123202275
      },
      "time": 372690
    },
    {
      "player": {
        "displayName": "James1975",
        "steamID": 76561198050829730
      },
      "time": 372710
    },
    {
      "player": {
        "displayName": "NachoBearSupreme",
        "steamID": 76561198161537597
      },
      "time": 375150
    },
    {
      "player": {
        "displayName": "freedterror",
        "steamID": 76561198262525283
      },
      "time": 378910
    },
    {
      "player": {
        "displayName": "boujore",
        "steamID": 76561198025889085
      },
      "time": 379300
    },
    {
      "player": {
        "displayName": "Leonx22",
        "steamID": 76561198154434188
      },
      "time": 379470
    },
    {
      "player": {
        "displayName": "YDOC02",
        "steamID": 76561198129955466
      },
      "time": 379730
    },
    {
      "player": {
        "displayName": "-Ω-",
        "steamID": 76561198065040574
      },
      "time": 380570
    },
    {
      "player": {
        "displayName": "jonathanalexanderorellana06",
        "steamID": 76561198409757755
      },
      "time": 380960
    },
    {
      "player": {
        "displayName": "Caiqs",
        "steamID": 76561198050398500
      },
      "time": 383560
    },
    {
      "player": {
        "displayName": "DefenderOfHyrule",
        "steamID": 76561198144159516
      },
      "time": 385980
    },
    {
      "player": {
        "displayName": "silvanthehedgehog50",
        "steamID": 76561198354127138
      },
      "time": 386070
    },
    {
      "player": {
        "displayName": "ezrawheeler118",
        "steamID": 76561198354905774
      },
      "time": 386110
    },
    {
      "player": {
        "displayName": "Valkyriem",
        "steamID": 76561198834936418
      },
      "time": 388250
    },
    {
      "player": {
        "displayName": "Zebulon759",
        "steamID": 76561198129657655
      },
      "time": 388500
    },
    {
      "player": {
        "displayName": "Energon Ironhide",
        "steamID": 76561198304638522
      },
      "time": 388780
    },
    {
      "player": {
        "displayName": "Darth Minty",
        "steamID": 76561198199378190
      },
      "time": 389390
    },
    {
      "player": {
        "displayName": "Fitroll7",
        "steamID": 76561198266797391
      },
      "time": 390160
    },
    {
      "player": {
        "displayName": "LeCangrejo",
        "steamID": 76561198093338574
      },
      "time": 390560
    },
    {
      "player": {
        "displayName": "Zero Kelvin",
        "steamID": 76561198112552497
      },
      "time": 391620
    },
    {
      "player": {
        "displayName": "_Colday_",
        "steamID": 76561198166889190
      },
      "time": 392560
    },
    {
      "player": {
        "displayName": "LelouchXV3",
        "steamID": 76561198265054890
      },
      "time": 395430
    },
    {
      "player": {
        "displayName": "CodRaven1728",
        "steamID": 76561198062687510
      },
      "time": 395550
    },
    {
      "player": {
        "displayName": "AK Tankmaster",
        "steamID": 76561198056505585
      },
      "time": 395930
    },
    {
      "player": {
        "displayName": "StolenSouls",
        "steamID": 76561198083623068
      },
      "time": 396250
    },
    {
      "player": {
        "displayName": "Banjo X",
        "steamID": 76561198050507466
      },
      "time": 396270
    },
    {
      "player": {
        "displayName": "Dimitrilium",
        "steamID": 76561198011974329
      },
      "time": 396360
    },
    {
      "player": {
        "displayName": "Sa1cor",
        "steamID": 76561198070818426
      },
      "time": 396370
    },
    {
      "player": {
        "displayName": "Buy_Skoirim",
        "steamID": 76561198181698905
      },
      "time": 396950
    },
    {
      "player": {
        "displayName": "Maerge",
        "steamID": 76561198327188860
      },
      "time": 398690
    },
    {
      "player": {
        "displayName": "Eppy37",
        "steamID": 76561198004384633
      },
      "time": 398880
    },
    {
      "player": {
        "displayName": "? ? ? ?",
        "steamID": 76561198067707036
      },
      "time": 399060
    },
    {
      "player": {
        "displayName": "El Renegade",
        "steamID": 76561198202971668
      },
      "time": 400270
    },
    {
      "player": {
        "displayName": "Acouya is a Synthetic Roo",
        "steamID": 76561198056956593
      },
      "time": 400630
    },
    {
      "player": {
        "displayName": "Zector1114",
        "steamID": 76561198086999554
      },
      "time": 400730
    },
    {
      "player": {
        "displayName": "guarniz.edwin",
        "steamID": 76561198279000305
      },
      "time": 401240
    },
    {
      "player": {
        "displayName": "Wyxix",
        "steamID": 76561198096598479
      },
      "time": 401300
    },
    {
      "player": {
        "displayName": "superdriftking13",
        "steamID": 76561198381283929
      },
      "time": 401300
    },
    {
      "player": {
        "displayName": "Transdimensional Loli :3",
        "steamID": 76561198126562732
      },
      "time": 401340
    },
    {
      "player": {
        "displayName": "shal",
        "steamID": 76561198012884084
      },
      "time": 402430
    },
    {
      "player": {
        "displayName": "Alex Chosen",
        "steamID": 76561197999606289
      },
      "time": 402450
    },
    {
      "player": {
        "displayName": "Rjiig123",
        "steamID": 76561198161810630
      },
      "time": 402720
    },
    {
      "player": {
        "displayName": "Asant",
        "steamID": 76561198380600285
      },
      "time": 402920
    },
    {
      "player": {
        "displayName": "Barakaldo188",
        "steamID": 76561198034575619
      },
      "time": 403370
    },
    {
      "player": {
        "displayName": "Koldheartz",
        "steamID": 76561198327943993
      },
      "time": 403470
    },
    {
      "player": {
        "displayName": "Fight Back",
        "steamID": 76561198242367632
      },
      "time": 404400
    },
    {
      "player": {
        "displayName": "vorador2",
        "steamID": 76561197994148936
      },
      "time": 405830
    },
    {
      "player": {
        "displayName": "Isurika",
        "steamID": 76561198046707554
      },
      "time": 407290
    },
    {
      "player": {
        "displayName": "jaredv1999",
        "steamID": 76561198384396499
      },
      "time": 407720
    },
    {
      "player": {
        "displayName": "SceneSavage",
        "steamID": 76561198303374157
      },
      "time": 407750
    },
    {
      "player": {
        "displayName": "HoloDreamer",
        "steamID": 76561198126856042
      },
      "time": 408540
    },
    {
      "player": {
        "displayName": "ATFx(Linux)",
        "steamID": 76561198127688335
      },
      "time": 408650
    },
    {
      "player": {
        "displayName": "DarthSpaceLord",
        "steamID": 76561198806765324
      },
      "time": 408650
    },
    {
      "player": {
        "displayName": "TOPoCAT",
        "steamID": 76561197999742804
      },
      "time": 409330
    },
    {
      "player": {
        "displayName": "XtracK22",
        "steamID": 76561198062843689
      },
      "time": 410010
    },
    {
      "player": {
        "displayName": "Covellite Caper",
        "steamID": 76561198034021530
      },
      "time": 410520
    },
    {
      "player": {
        "displayName": "DrunkPinaColada",
        "steamID": 76561198176207295
      },
      "time": 411260
    },
    {
      "player": {
        "displayName": "GalacticSpike",
        "steamID": 76561198207869735
      },
      "time": 413490
    },
    {
      "player": {
        "displayName": "ムDequu",
        "steamID": 76561198353824164
      },
      "time": 413650
    },
    {
      "player": {
        "displayName": "Terrapin Turtle",
        "steamID": 76561198154078481
      },
      "time": 414160
    },
    {
      "player": {
        "displayName": "Mr. Doon",
        "steamID": 76561198050599225
      },
      "time": 414200
    },
    {
      "player": {
        "displayName": "MrMii",
        "steamID": 76561198065540876
      },
      "time": 414280
    },
    {
      "player": {
        "displayName": "Private Soyboy",
        "steamID": 76561198261197741
      },
      "time": 414480
    },
    {
      "player": {
        "displayName": "Wielki Komarcini",
        "steamID": 76561198037636423
      },
      "time": 414760
    },
    {
      "player": {
        "displayName": "ZorexBlade",
        "steamID": 76561198314551727
      },
      "time": 414830
    },
    {
      "player": {
        "displayName": "iagodavid299",
        "steamID": 76561198222627628
      },
      "time": 415020
    },
    {
      "player": {
        "displayName": "SilentFrame",
        "steamID": 76561198077998205
      },
      "time": 416900
    },
    {
      "player": {
        "displayName": "EP1CZ0D",
        "steamID": 76561198080045536
      },
      "time": 418400
    },
    {
      "player": {
        "displayName": "Nathan, some Hedgehog",
        "steamID": 76561198120380210
      },
      "time": 418810
    },
    {
      "player": {
        "displayName": "暁 Pain",
        "steamID": 76561198139395117
      },
      "time": 419530
    },
    {
      "player": {
        "displayName": "FluffyTheZombie",
        "steamID": 76561198134309424
      },
      "time": 421780
    },
    {
      "player": {
        "displayName": "Monster Girls Cure Depression",
        "steamID": 76561198125950078
      },
      "time": 423570
    },
    {
      "player": {
        "displayName": "Zoe God",
        "steamID": 76561198196168238
      },
      "time": 424940
    },
    {
      "player": {
        "displayName": "FlamingFlamingo",
        "steamID": 76561198091808567
      },
      "time": 427080
    },
    {
      "player": {
        "displayName": "Kirito",
        "steamID": 76561198309621360
      },
      "time": 429640
    },
    {
      "player": {
        "displayName": "bobby8955",
        "steamID": 76561198229420824
      },
      "time": 429820
    },
    {
      "player": {
        "displayName": "jmec6",
        "steamID": 76561198403155597
      },
      "time": 432270
    },
    {
      "player": {
        "displayName": "CamLewa",
        "steamID": 76561198305655691
      },
      "time": 432470
    },
    {
      "player": {
        "displayName": "mr sex goblin",
        "steamID": 76561198115056674
      },
      "time": 433240
    },
    {
      "player": {
        "displayName": "Avatarmushi",
        "steamID": 76561198280123363
      },
      "time": 433790
    },
    {
      "player": {
        "displayName": "efren1215",
        "steamID": 76561198831851401
      },
      "time": 434000
    },
    {
      "player": {
        "displayName": "resistance is futile",
        "steamID": 76561198146782074
      },
      "time": 434360
    },
    {
      "player": {
        "displayName": "Overlord",
        "steamID": 76561198433725794
      },
      "time": 434630
    },
    {
      "player": {
        "displayName": "DerDaniel",
        "steamID": 76561198154283148
      },
      "time": 434750
    },
    {
      "player": {
        "displayName": "Pharamobius",
        "steamID": 76561198432672954
      },
      "time": 434770
    },
    {
      "player": {
        "displayName": "Kiatsu",
        "steamID": 76561198095491517
      },
      "time": 436010
    },
    {
      "player": {
        "displayName": "thejoker2082",
        "steamID": 76561198328605386
      },
      "time": 437000
    },
    {
      "player": {
        "displayName": "NeonUmbreon",
        "steamID": 76561198119697124
      },
      "time": 437320
    },
    {
      "player": {
        "displayName": "Damashii",
        "steamID": 76561198129120223
      },
      "time": 437390
    },
    {
      "player": {
        "displayName": "EnderKill98",
        "steamID": 76561198119440545
      },
      "time": 437650
    },
    {
      "player": {
        "displayName": "TonksM",
        "steamID": 76561198029095915
      },
      "time": 438400
    },
    {
      "player": {
        "displayName": "ShadySandwichGuy",
        "steamID": 76561198054598286
      },
      "time": 439590
    },
    {
      "player": {
        "displayName": "[NCC] IcemaN",
        "steamID": 76561198067074709
      },
      "time": 440790
    },
    {
      "player": {
        "displayName": "Lumario",
        "steamID": 76561198092436913
      },
      "time": 440900
    },
    {
      "player": {
        "displayName": "gugaos10",
        "steamID": 76561198453893237
      },
      "time": 441430
    },
    {
      "player": {
        "displayName": "Arrow_Tiler_YT",
        "steamID": 76561198366583400
      },
      "time": 441990
    },
    {
      "player": {
        "displayName": "drenchjet",
        "steamID": 76561198803498632
      },
      "time": 443570
    },
    {
      "player": {
        "displayName": "Racerman2001",
        "steamID": 76561198090710888
      },
      "time": 445160
    },
    {
      "player": {
        "displayName": "Banagher_",
        "steamID": 76561198046396038
      },
      "time": 445590
    },
    {
      "player": {
        "displayName": "fran_reyes09",
        "steamID": 76561198849183597
      },
      "time": 445880
    },
    {
      "player": {
        "displayName": "Iced Lemon",
        "steamID": 76561198287486690
      },
      "time": 446730
    },
    {
      "player": {
        "displayName": "Shingo Twingo",
        "steamID": 76561198080349818
      },
      "time": 446740
    },
    {
      "player": {
        "displayName": "Alexander Mirkov",
        "steamID": 76561198319796246
      },
      "time": 447050
    },
    {
      "player": {
        "displayName": "Knowledge",
        "steamID": 76561198072149839
      },
      "time": 447690
    },
    {
      "player": {
        "displayName": "Pirate",
        "steamID": 76561198356374110
      },
      "time": 448490
    },
    {
      "player": {
        "displayName": "killer97188",
        "steamID": 76561198084452417
      },
      "time": 448610
    },
    {
      "player": {
        "displayName": "KróliczekYT",
        "steamID": 76561198179574794
      },
      "time": 448660
    },
    {
      "player": {
        "displayName": "retuy13",
        "steamID": 76561198190097837
      },
      "time": 448870
    },
    {
      "player": {
        "displayName": "zakhep44",
        "steamID": 76561198299492657
      },
      "time": 450060
    },
    {
      "player": {
        "displayName": "Dark_ION57_вук",
        "steamID": 76561198025480120
      },
      "time": 450570
    },
    {
      "player": {
        "displayName": "xpenny1 (1473)",
        "steamID": 76561198095002054
      },
      "time": 454120
    },
    {
      "player": {
        "displayName": "Girouphare #9",
        "steamID": 76561198123848425
      },
      "time": 454290
    },
    {
      "player": {
        "displayName": "OLIVEIRA",
        "steamID": 76561198225258676
      },
      "time": 454520
    },
    {
      "player": {
        "displayName": "GameStarLion",
        "steamID": 76561198117098346
      },
      "time": 454570
    },
    {
      "player": {
        "displayName": "ederino120",
        "steamID": 76561198318041793
      },
      "time": 454870
    },
    {
      "player": {
        "displayName": "a wild rudik",
        "steamID": 76561198086416291
      },
      "time": 460350
    },
    {
      "player": {
        "displayName": "A G A R A G Ã",
        "steamID": 76561198269449627
      },
      "time": 462360
    },
    {
      "player": {
        "displayName": "SandGator17",
        "steamID": 76561198170039661
      },
      "time": 463330
    },
    {
      "player": {
        "displayName": "AGG ALIENS ISO AVP",
        "steamID": 76561198121652551
      },
      "time": 463420
    },
    {
      "player": {
        "displayName": "theninjacat799",
        "steamID": 76561198110843048
      },
      "time": 465920
    },
    {
      "player": {
        "displayName": "Ennik",
        "steamID": 76561197997268689
      },
      "time": 470720
    },
    {
      "player": {
        "displayName": "supersushicat1",
        "steamID": 76561198153849122
      },
      "time": 470780
    },
    {
      "player": {
        "displayName": "hacxinator101",
        "steamID": 76561198109103009
      },
      "time": 473540
    },
    {
      "player": {
        "displayName": "Siddey10",
        "steamID": 76561198027365378
      },
      "time": 477160
    },
    {
      "player": {
        "displayName": "Dr. Reid",
        "steamID": 76561198091894706
      },
      "time": 477260
    },
    {
      "player": {
        "displayName": "AbacateBolado",
        "steamID": 76561198332655594
      },
      "time": 478970
    },
    {
      "player": {
        "displayName": "mine152",
        "steamID": 76561198338802362
      },
      "time": 480390
    },
    {
      "player": {
        "displayName": "Sixolu-Veks",
        "steamID": 76561198049555150
      },
      "time": 480790
    },
    {
      "player": {
        "displayName": "Estre",
        "steamID": 76561198151690909
      },
      "time": 481270
    },
    {
      "player": {
        "displayName": "Jackalspeed",
        "steamID": 76561198069738700
      },
      "time": 481850
    },
    {
      "player": {
        "displayName": "Motorhelm",
        "steamID": 76561198321429740
      },
      "time": 482110
    },
    {
      "player": {
        "displayName": "TheBirdman5555",
        "steamID": 76561198410931545
      },
      "time": 483600
    },
    {
      "player": {
        "displayName": "Zephyr The Racer",
        "steamID": 76561198091653993
      },
      "time": 484790
    },
    {
      "player": {
        "displayName": "Tkach",
        "steamID": 76561198146514915
      },
      "time": 487920
    },
    {
      "player": {
        "displayName": "Riley",
        "steamID": 76561198090372870
      },
      "time": 489910
    },
    {
      "player": {
        "displayName": "Xeinok",
        "steamID": 76561197983791150
      },
      "time": 491580
    },
    {
      "player": {
        "displayName": "misalviano",
        "steamID": 76561198129287709
      },
      "time": 492680
    },
    {
      "player": {
        "displayName": "Sandsword 13",
        "steamID": 76561198356850300
      },
      "time": 494020
    },
    {
      "player": {
        "displayName": "ΩScoots_PootsΩ",
        "steamID": 76561198078975094
      },
      "time": 495670
    },
    {
      "player": {
        "displayName": "blin blin boy cs.money",
        "steamID": 76561198335350853
      },
      "time": 507560
    },
    {
      "player": {
        "displayName": "Mr.Fox500",
        "steamID": 76561198133719962
      },
      "time": 508370
    },
    {
      "player": {
        "displayName": "MrVavlo",
        "steamID": 76561198068544302
      },
      "time": 510270
    },
    {
      "player": {
        "displayName": "Losi",
        "steamID": 76561198153631994
      },
      "time": 511350
    },
    {
      "player": {
        "displayName": "Nachimeko",
        "steamID": 76561198263804833
      },
      "time": 512600
    },
    {
      "player": {
        "displayName": "M4RC0",
        "steamID": 76561198169853779
      },
      "time": 513960
    },
    {
      "player": {
        "displayName": "Kollan11",
        "steamID": 76561198123476156
      },
      "time": 516770
    },
    {
      "player": {
        "displayName": "carcrasher003",
        "steamID": 76561198373558412
      },
      "time": 518180
    },
    {
      "player": {
        "displayName": "wojciechweis",
        "steamID": 76561198851558573
      },
      "time": 519540
    },
    {
      "player": {
        "displayName": "BarricadeSkywalker",
        "steamID": 76561197996404097
      },
      "time": 520060
    },
    {
      "player": {
        "displayName": "Lunchism",
        "steamID": 76561198052002649
      },
      "time": 522390
    },
    {
      "player": {
        "displayName": "Nyx The Nargacuga",
        "steamID": 76561198194656802
      },
      "time": 523010
    },
    {
      "player": {
        "displayName": "Player Duke",
        "steamID": 76561198141660016
      },
      "time": 527470
    },
    {
      "player": {
        "displayName": "SamuraiBR opencases.cheap",
        "steamID": 76561198418395788
      },
      "time": 528470
    },
    {
      "player": {
        "displayName": "Freezesixty",
        "steamID": 76561198079547148
      },
      "time": 529030
    },
    {
      "player": {
        "displayName": "zachcat128",
        "steamID": 76561198411340636
      },
      "time": 530450
    },
    {
      "player": {
        "displayName": "Arkany",
        "steamID": 76561198018565503
      },
      "time": 533740
    },
    {
      "player": {
        "displayName": "gdaykiller",
        "steamID": 76561198047571093
      },
      "time": 533770
    },
    {
      "player": {
        "displayName": "KemoMaty",
        "steamID": 76561198141185964
      },
      "time": 534210
    },
    {
      "player": {
        "displayName": "Leuca©",
        "steamID": 76561198062356753
      },
      "time": 537640
    },
    {
      "player": {
        "displayName": "FrozenMG5",
        "steamID": 76561198109435037
      },
      "time": 538340
    },
    {
      "player": {
        "displayName": "UltraLeevi",
        "steamID": 76561198346646547
      },
      "time": 543390
    },
    {
      "player": {
        "displayName": "Zenji",
        "steamID": 76561198123363975
      },
      "time": 544730
    },
    {
      "player": {
        "displayName": "Exspirow",
        "steamID": 76561198438974980
      },
      "time": 547810
    },
    {
      "player": {
        "displayName": "JackSparon10",
        "steamID": 76561198278021742
      },
      "time": 550330
    },
    {
      "player": {
        "displayName": "timeroller",
        "steamID": 76561198148372501
      },
      "time": 552840
    },
    {
      "player": {
        "displayName": "Concorde",
        "steamID": 76561198079743502
      },
      "time": 556380
    },
    {
      "player": {
        "displayName": "Himikko | 逢",
        "steamID": 76561197962847082
      },
      "time": 561090
    },
    {
      "player": {
        "displayName": "KazaKillin",
        "steamID": 76561198076704258
      },
      "time": 561730
    },
    {
      "player": {
        "displayName": "matt.abbott",
        "steamID": 76561198255744970
      },
      "time": 562570
    },
    {
      "player": {
        "displayName": "Looker",
        "steamID": 76561198087515178
      },
      "time": 567440
    },
    {
      "player": {
        "displayName": "Shavter",
        "steamID": 76561198058406939
      },
      "time": 572820
    },
    {
      "player": {
        "displayName": "Alex_Bik",
        "steamID": 76561198272801834
      },
      "time": 573400
    },
    {
      "player": {
        "displayName": "Dave's 1 World",
        "steamID": 76561198061774705
      },
      "time": 574010
    },
    {
      "player": {
        "displayName": "Aastran",
        "steamID": 76561198119179836
      },
      "time": 574150
    },
    {
      "player": {
        "displayName": "Sean the Piano Man",
        "steamID": 76561198089135951
      },
      "time": 577990
    },
    {
      "player": {
        "displayName": "Orlonditi",
        "steamID": 76561198132882589
      },
      "time": 581440
    },
    {
      "player": {
        "displayName": "TheSuperSaiyanRose",
        "steamID": 76561198369399750
      },
      "time": 591930
    },
    {
      "player": {
        "displayName": "[CobraRacingCrew] GT500Cobra",
        "steamID": 76561198254504275
      },
      "time": 595050
    },
    {
      "player": {
        "displayName": "☆Thug",
        "steamID": 76561198155583439
      },
      "time": 608150
    },
    {
      "player": {
        "displayName": "ValkenVugen",
        "steamID": 76561198182207771
      },
      "time": 612410
    },
    {
      "player": {
        "displayName": "nsr110",
        "steamID": 76561198043386295
      },
      "time": 612800
    },
    {
      "player": {
        "displayName": "ahenager",
        "steamID": 76561198272334383
      },
      "time": 615960
    },
    {
      "player": {
        "displayName": "nico",
        "steamID": 76561198041500742
      },
      "time": 638430
    },
    {
      "player": {
        "displayName": "RaiderZulu",
        "steamID": 76561198107572699
      },
      "time": 655580
    },
    {
      "player": {
        "displayName": "Kire",
        "steamID": 76561198306556008
      },
      "time": 656720
    },
    {
      "player": {
        "displayName": "Gmor-4",
        "steamID": 76561198131762098
      },
      "time": 659820
    },
    {
      "player": {
        "displayName": "Alex from AK #RemoveRandomCrits",
        "steamID": 76561198120426715
      },
      "time": 677070
    },
    {
      "player": {
        "displayName": "HIGH FIDELITY M E M E S on FB",
        "steamID": 76561198120657050
      },
      "time": 685660
    },
    {
      "player": {
        "displayName": "Teku Squid",
        "steamID": 76561198308399151
      },
      "time": 692610
    },
    {
      "player": {
        "displayName": "frankzirk",
        "steamID": 76561198134795361
      },
      "time": 719490
    },
    {
      "player": {
        "displayName": "<KadenzFermata> | TakeshiKagami",
        "steamID": 76561198352810660
      },
      "time": 729430
    },
    {
      "player": {
        "displayName": "DriftTechno10gy",
        "steamID": 76561198421764346
      },
      "time": 733370
    },
    {
      "player": {
        "displayName": "N-Jin",
        "steamID": 76561198085054630
      },
      "time": 756330
    },
    {
      "player": {
        "displayName": "Brittney V",
        "steamID": 76561198065101309
      },
      "time": 762350
    },
    {
      "player": {
        "displayName": "TheNekoMimiGamer",
        "steamID": 76561198277792494
      },
      "time": 769990
    },
    {
      "player": {
        "displayName": "Hatsune ミクsama",
        "steamID": 76561198214924995
      },
      "time": 773800
    },
    {
      "player": {
        "displayName": "[RET] Ex-Captain Ꮶ. Madrek",
        "steamID": 76561198122870428
      },
      "time": 853460
    },
    {
      "player": {
        "displayName": "CodeMaster",
        "steamID": 76561198120690777
      },
      "time": 904840
    },
    {
      "player": {
        "displayName": "Toddthefox17",
        "steamID": 76561198281693546
      },
      "time": 1042810
    },
    {
      "player": {
        "displayName": "ZeriouZ",
        "steamID": 76561198218141028
      },
      "time": 1095080
    },
    {
      "player": {
        "displayName": "mech morph pony",
        "steamID": 76561198177310525
      },
      "time": 1171090
    }
  ]
}