{
  "author": {
    "displayName": "[unknown]",
    "steamID": 76561198060577567
  },
  "displayName": "Fast Screwing",
  "id": 419328695,
  "description": "A short turnaround track",
  "fileName": "distorsion",
  "upvotes": 107,
  "downvotes": 31,
  "leaderboard": [
    {
      "player": {
        "displayName": "IllKIllU",
        "steamID": 76561198216635512
      },
      "time": 50620
    },
    {
      "player": {
        "displayName": "Rú",
        "steamID": 76561198097996356
      },
      "time": 55720
    },
    {
      "player": {
        "displayName": "ferreus",
        "steamID": 76561198040630941
      },
      "time": 72290
    },
    {
      "player": {
        "displayName": "noah",
        "steamID": 76561198129061896
      },
      "time": 79700
    },
    {
      "player": {
        "displayName": "Protagonist",
        "steamID": 76561198075627683
      },
      "time": 100110
    },
    {
      "player": {
        "displayName": "Phazonium",
        "steamID": 76561198025024919
      },
      "time": 100240
    },
    {
      "player": {
        "displayName": "KillPaladin",
        "steamID": 76561198042158665
      },
      "time": 101100
    },
    {
      "player": {
        "displayName": "TheLyricLeo",
        "steamID": 76561198093773159
      },
      "time": 106250
    },
    {
      "player": {
        "displayName": "pigpenguin",
        "steamID": 76561198010296669
      },
      "time": 107330
    },
    {
      "player": {
        "displayName": "RaiderZulu",
        "steamID": 76561198107572699
      },
      "time": 109850
    },
    {
      "player": {
        "displayName": "Zarifi",
        "steamID": 76561197994658692
      },
      "time": 109950
    },
    {
      "player": {
        "displayName": "SpicyMiku-chan",
        "steamID": 76561198017945328
      },
      "time": 110730
    },
    {
      "player": {
        "displayName": "Ejotapg",
        "steamID": 76561198019596311
      },
      "time": 111900
    },
    {
      "player": {
        "displayName": "nico",
        "steamID": 76561198041500742
      },
      "time": 116840
    },
    {
      "player": {
        "displayName": "DefenderOfHyrule",
        "steamID": 76561198144159516
      },
      "time": 135140
    },
    {
      "player": {
        "displayName": "Nerf",
        "steamID": 76561198137753179
      },
      "time": 139100
    },
    {
      "player": {
        "displayName": "FRaXure",
        "steamID": 76561198062392816
      },
      "time": 155230
    },
    {
      "player": {
        "displayName": "ash",
        "steamID": 76561198025607548
      },
      "time": 157540
    },
    {
      "player": {
        "displayName": "jason",
        "steamID": 76561198182286527
      },
      "time": 161750
    },
    {
      "player": {
        "displayName": "Phil_",
        "steamID": 76561198041597428
      },
      "time": 163120
    },
    {
      "player": {
        "displayName": "Arenev",
        "steamID": 76561198072259429
      },
      "time": 165600
    },
    {
      "player": {
        "displayName": "GruntZone360",
        "steamID": 76561198120531024
      },
      "time": 168980
    },
    {
      "player": {
        "displayName": "sundbrya101",
        "steamID": 76561198046353321
      },
      "time": 173120
    },
    {
      "player": {
        "displayName": "Zebulon759",
        "steamID": 76561198129657655
      },
      "time": 191080
    },
    {
      "player": {
        "displayName": "Jaxenstein",
        "steamID": 76561198107971104
      },
      "time": 195390
    },
    {
      "player": {
        "displayName": "BR3CH3 encleseve",
        "steamID": 76561198030019606
      },
      "time": 196070
    },
    {
      "player": {
        "displayName": "Silverheart",
        "steamID": 76561198094885141
      },
      "time": 198750
    },
    {
      "player": {
        "displayName": "shroomz",
        "steamID": 76561198006983188
      },
      "time": 201550
    },
    {
      "player": {
        "displayName": "RainyOdin",
        "steamID": 76561198120627890
      },
      "time": 204870
    },
    {
      "player": {
        "displayName": "TestaDpazzO",
        "steamID": 76561198019481418
      },
      "time": 206540
    },
    {
      "player": {
        "displayName": "TikeyNFS",
        "steamID": 76561198165857333
      },
      "time": 224940
    },
    {
      "player": {
        "displayName": "JoJo Reference",
        "steamID": 76561198052346385
      },
      "time": 225090
    },
    {
      "player": {
        "displayName": "『』",
        "steamID": 76561198139436636
      },
      "time": 239280
    },
    {
      "player": {
        "displayName": "𐱅𐰇𐰼𐰇𐰚 𐱅𐰚𐰀 𐰋𐰼𐰇𐱅𐰀",
        "steamID": 76561198135922531
      },
      "time": 241430
    },
    {
      "player": {
        "displayName": "FluxPrototype46",
        "steamID": 76561198119360746
      },
      "time": 246820
    },
    {
      "player": {
        "displayName": "Lightshift",
        "steamID": 76561198045491187
      },
      "time": 247340
    },
    {
      "player": {
        "displayName": "Onetimetwotimes",
        "steamID": 76561198126185552
      },
      "time": 260410
    },
    {
      "player": {
        "displayName": "Hudbus",
        "steamID": 76561198193921543
      },
      "time": 262930
    },
    {
      "player": {
        "displayName": "yozpoz",
        "steamID": 76561198050727878
      },
      "time": 265690
    },
    {
      "player": {
        "displayName": "Bunker475",
        "steamID": 76561198148309691
      },
      "time": 273580
    },
    {
      "player": {
        "displayName": "Shray",
        "steamID": 76561198071320228
      },
      "time": 366360
    },
    {
      "player": {
        "displayName": "Adewale Kingsley",
        "steamID": 76561198075367663
      },
      "time": 633110
    }
  ]
}